bamboo_lib/VERSION
bamboo_lib/__init__.py
bamboo_lib/consts.py
bamboo_lib/exceptions.py
bamboo_lib/helpers.py
bamboo_lib/logger.py
bamboo_lib/models.py
bamboo_lib/params_helper.py
bamboo_lib/steps.py
bamboo_lib/connectors/__init__.py
bamboo_lib/connectors/models.py
bamboo_lib/connectors/drivers/__init__.py
bamboo_lib/connectors/drivers/clickhouse.py
bamboo_lib/connectors/drivers/database.py
bamboo_lib/connectors/drivers/filetransfer.py
bamboo_lib/connectors/drivers/gcs.py
bamboo_lib/connectors/drivers/http.py
bamboo_lib/connectors/drivers/monet.py
bamboo_lib/connectors/drivers/postgres.py
bamboo_lib/connectors/drivers/redis.py
bamboo_lib/connectors/drivers/s3.py
bamboo_lib/connectors/drivers/ssh_tunnel.py
bamboo_lib/pipelines/__init__.py
bamboo_lib/pipelines/pums/__init__.py
bamboo_lib/pipelines/pums/mondrian.py
bamboo_lib/pipelines/pums/pums_runner.py
bamboo_lib/pipelines/pums/cleaning/__init__.py
bamboo_lib/pipelines/pums/cleaning/cleaner.py
bamboo_lib/pipelines/pums/cleaning/io_converter.py
bamboo_lib/pipelines/pums/cleaning/puma.py
bamboo_lib/pipelines/pums/cleaning/puma_helper.py
bamboo_lib/pipelines/pums/cleaning/util.py
bamboo_lib/scratch/__init__.py
bamboo_lib/scratch/gen_rca.py
bamboo_lib/scratch/pums_core_schema.py
bamboo_lib/scratch/rw2.py
bamboo_lib/scratch/schema_gen.py
bamboo_lib/scratch/simple_rca.py
bamboo_lib/virtualschema/__init__.py
bamboo_lib/virtualschema/models.py
tests/__init__.py
tests/test_converts_relative_path_to_absolute_path.py
tests/test_default_params.py
tests/test_easy_pipeline.py
tests/test_easy_pipeline_loops.py
tests/test_gcs_connector.py
tests/test_http_dl_dir.py
tests/test_multi_source_conn_dl.py
tests/test_parallel_pipeline.py
tests/test_pipelines.py
tests/test_result_key.py
tests/test_s3_connector.py
tests/test_unzip_to_folder_and_cleanup.py
bamboo_lib-0.0.38.dist-info/LICENSE
bamboo_lib-0.0.38.dist-info/METADATA
bamboo_lib-0.0.38.dist-info/WHEEL
bamboo_lib-0.0.38.dist-info/top_level.txt
bamboo_lib-0.0.38.dist-info/RECORD
