Metadata-Version: 2.1
Name: bamboo-lib
Version: 0.0.38
Summary: Python ETL library
Home-page: https://github.com/Datawheel/bamboo-lib
Author: Jonathan Speiser
Author-email: jonathan@datawheel.us
License: All Rights Reserved
Platform: UNKNOWN
Classifier: Programming Language :: Python :: 3
Classifier: Operating System :: OS Independent
Requires-Dist: pandas ==1.1.4
Requires-Dist: sqlalchemy ==1.2.10
Requires-Dist: data-catapult
Requires-Dist: paramiko ==2.4.1
Requires-Dist: sshtunnel ==0.1.4
Requires-Dist: redis ==2.10.6
Requires-Dist: pathos ==0.2.5
Requires-Dist: geopandas ==0.5.1
Requires-Dist: pytest
Requires-Dist: sphinx-rtd-theme ==0.4.3
Requires-Dist: google-cloud-storage ==1.18.0
Requires-Dist: cryptography ==2.3
Requires-Dist: progressbar ==2.5
Requires-Dist: boto3 ==1.12.43
